langkit/cache/sentence_transformers.py
langkit/cache/setfit_model.py
langkit/callbacks/library.py
langkit/callbacks/webhook.py
langkit/core/context.py
langkit/core/generator_value.py
langkit/core/metric.py
langkit/core/metric_runner.py
langkit/core/validation.py
langkit/core/workflow.py
langkit/metrics/embedding_generation.py
langkit/metrics/embeddings_types.py
langkit/metrics/embeddings_utils.py
langkit/metrics/injections.py
langkit/metrics/injections_chroma.py
langkit/metrics/injections_chroma_twoclass.py
langkit/metrics/input_context_similarity.py
langkit/metrics/input_output_similarity.py
langkit/metrics/library.py
langkit/metrics/malicious.py
langkit/metrics/pca_metric.py
langkit/metrics/pii.py
langkit/metrics/regexes/__init__.py
langkit/metrics/regexes/pattern_groups.json
langkit/metrics/regexes/regex_loader.py
langkit/metrics/regexes/regexes.py
langkit/metrics/response_hallucination.py
langkit/metrics/sentiment_polarity.py
langkit/metrics/text_statistics.py
langkit/metrics/text_statistics_types.py
langkit/metrics/themes/additional_data.py
langkit/metrics/themes/themes.json
langkit/metrics/themes/themes.py
langkit/metrics/token.py
langkit/metrics/topic.py
langkit/metrics/topic_chroma.py
langkit/metrics/topic_setfit.py
langkit/metrics/topic_toolkit.py
langkit/metrics/topic_twoclass_chroma.py
langkit/metrics/toxicity.py
langkit/metrics/toxicity_onnx.py
langkit/metrics/toxicity_setfit.py
langkit/metrics/util.py
langkit/metrics/wf_option_util.py
langkit/metrics/whylogs_compat.py
langkit/onnx_encoder.py
langkit/openai/__init__.py
langkit/openai/hallucination_types.py
langkit/openai/openai.py
langkit/tensor_util.py
langkit/transformer.py
langkit/validators/comparison.py
langkit/validators/library.py
whylabs_llm_toolkit/__init__.py
whylabs_llm_toolkit/asset_download.py
whylabs_llm_toolkit/data/__init__.py
whylabs_llm_toolkit/data/data.py
whylabs_llm_toolkit/data/datasets/c_3p_dataset.py
whylabs_llm_toolkit/data/datasets/code_dataset.py
whylabs_llm_toolkit-0.1.37.dist-info/METADATA
whylabs_llm_toolkit-0.1.37.dist-info/WHEEL
whylabs_llm_toolkit-0.1.37.dist-info/RECORD
