Metadata-Version: 2.1
Name: whylabs-llm-toolkit
Version: 0.1.37
Summary: Utilities for harm dataset generation
Author: Felipe Adachi
Author-email: felipeadachi@gmail.com
Requires-Python: >=3.9,<3.12
Classifier: Programming Language :: Python :: 3
Classifier: Programming Language :: Python :: 3.9
Classifier: Programming Language :: Python :: 3.10
Classifier: Programming Language :: Python :: 3.11
Provides-Extra: eval
Provides-Extra: infer
Provides-Extra: torch
Requires-Dist: chromadb (==0.5.5) ; extra == "eval" or extra == "infer"
Requires-Dist: databricks-sdk (>=0.25.1,<0.26.0) ; extra == "eval"
Requires-Dist: evaluate (>=0.4.0,<0.5.0) ; extra == "infer"
Requires-Dist: huggingface-hub (>=0.23.5,<0.24.0) ; extra == "infer"
Requires-Dist: matplotlib (>=3.8.4,<4.0.0) ; extra == "eval"
Requires-Dist: mlflow (>=2.11.3,<3.0.0) ; extra == "eval"
Requires-Dist: nltk (>=3.9,<4.0) ; extra == "infer"
Requires-Dist: numpy ; extra == "infer"
Requires-Dist: onnx (>=1.17.0,<2.0.0) ; extra == "infer"
Requires-Dist: openai (>=0.27.6,<2.0.0) ; extra == "infer"
Requires-Dist: optimum[exporters,onnxruntime] (==1.23.1) ; extra == "eval" or extra == "infer"
Requires-Dist: pandas ; extra == "eval" or extra == "infer"
Requires-Dist: presidio-analyzer (==2.2.352) ; extra == "infer"
Requires-Dist: presidio-anonymizer (==2.2.352) ; extra == "infer"
Requires-Dist: pyarrow (>=15.0.2,<16.0.0)
Requires-Dist: pydantic (>=2.6.1,<3.0.0)
Requires-Dist: pydantic-settings (>=2.2.1,<3.0.0)
Requires-Dist: python-dotenv (>=1.0.1,<2.0.0) ; extra == "eval"
Requires-Dist: scikit-learn (>=1.4.1.post1,<2.0.0) ; extra == "eval"
Requires-Dist: sentence-transformers (>=3.2.0,<4.0.0) ; extra == "eval" or extra == "infer"
Requires-Dist: setfit (>=1.1.0,<2.0.0) ; extra == "infer"
Requires-Dist: tenacity (>=8.2.3,<9.0.0)
Requires-Dist: tiktoken (==0.6.0) ; extra == "infer"
Requires-Dist: torch (==2.2.1) ; extra == "torch"
Requires-Dist: transformers (>=4.43.0,<5.0.0) ; extra == "eval" or extra == "infer"
Requires-Dist: whylabs-client (>=0.6.6,<0.7.0)
Requires-Dist: whylabs-textstat (>=0.7.4,<0.8.0) ; extra == "infer"
Requires-Dist: whylogs (>=1.4.4,<2.0.0)
